odoo/addons/account_fiscal_position_usage_group/README.rst
odoo/addons/account_fiscal_position_usage_group/__init__.py
odoo/addons/account_fiscal_position_usage_group/__manifest__.py
odoo/addons/account_fiscal_position_usage_group/demo/account_fiscal_position.xml
odoo/addons/account_fiscal_position_usage_group/demo/res_groups.xml
odoo/addons/account_fiscal_position_usage_group/i18n/account_fiscal_position_usage_group.pot
odoo/addons/account_fiscal_position_usage_group/i18n/fr.po
odoo/addons/account_fiscal_position_usage_group/i18n/pt.po
odoo/addons/account_fiscal_position_usage_group/models/__init__.py
odoo/addons/account_fiscal_position_usage_group/models/account_fiscal_position.py
odoo/addons/account_fiscal_position_usage_group/models/account_fiscal_position_template.py
odoo/addons/account_fiscal_position_usage_group/models/account_invoice.py
odoo/addons/account_fiscal_position_usage_group/models/res_partner.py
odoo/addons/account_fiscal_position_usage_group/readme/CONFIGURE.rst
odoo/addons/account_fiscal_position_usage_group/readme/CONTRIBUTORS.rst
odoo/addons/account_fiscal_position_usage_group/readme/DESCRIPTION.rst
odoo/addons/account_fiscal_position_usage_group/static/description/account_fiscal_position_form.png
odoo/addons/account_fiscal_position_usage_group/static/description/account_fiscal_position_template_form.png
odoo/addons/account_fiscal_position_usage_group/static/description/icon.png
odoo/addons/account_fiscal_position_usage_group/static/description/index.html
odoo/addons/account_fiscal_position_usage_group/static/description/warning_access_limited.png
odoo/addons/account_fiscal_position_usage_group/tests/__init__.py
odoo/addons/account_fiscal_position_usage_group/tests/test_module.py
odoo/addons/account_fiscal_position_usage_group/views/view_account_fiscal_position.xml
odoo/addons/account_fiscal_position_usage_group/views/view_account_fiscal_position_template.xml
odoo12_addon_account_fiscal_position_usage_group-12.0.1.0.0.99.dev8.dist-info/METADATA
odoo12_addon_account_fiscal_position_usage_group-12.0.1.0.0.99.dev8.dist-info/WHEEL
odoo12_addon_account_fiscal_position_usage_group-12.0.1.0.0.99.dev8.dist-info/top_level.txt
odoo12_addon_account_fiscal_position_usage_group-12.0.1.0.0.99.dev8.dist-info/RECORD
