Metadata-Version: 2.1
Name: odoo12-addon-account-fiscal-position-usage-group
Version: 12.0.1.0.0.99.dev8
Summary: Limit the usage of fiscal positions to defined groups members
Home-page: https://github.com/OCA/account-fiscal-rule
Author: GRAP,Odoo Community Association (OCA)
Author-email: support@odoo-community.org
License: AGPL-3
Platform: UNKNOWN
Classifier: Programming Language :: Python
Classifier: Framework :: Odoo
Classifier: Framework :: Odoo :: 12.0
Classifier: License :: OSI Approved :: GNU Affero General Public License v3
Classifier: Development Status :: 4 - Beta
Requires-Python: >=3.5
Requires-Dist: odoo12-addon-account-coa-menu
Requires-Dist: odoo <12.1dev,>=12.0a
